simplebot_lyrics.py
simplebot_lyrics-1.2.1.dist-info/LICENSE
simplebot_lyrics-1.2.1.dist-info/METADATA
simplebot_lyrics-1.2.1.dist-info/WHEEL
simplebot_lyrics-1.2.1.dist-info/entry_points.txt
simplebot_lyrics-1.2.1.dist-info/top_level.txt
simplebot_lyrics-1.2.1.dist-info/RECORD
